chargeamps/__init__.py
chargeamps/base.py
chargeamps/cli.py
chargeamps/external.py
chargeamps/local.py
chargeamps/models.py
chargeamps-1.8.2.dist-info/LICENSE
chargeamps-1.8.2.dist-info/METADATA
chargeamps-1.8.2.dist-info/WHEEL
chargeamps-1.8.2.dist-info/entry_points.txt
chargeamps-1.8.2.dist-info/RECORD
