Metadata-Version: 2.1
Name: chargeamps
Version: 1.8.2
Summary: Charge-Amps API bindings for Python
Home-page: https://github.com/kirei/python-chargeamps
License: BSD-2-Clause
Keywords: ev
Author: Jakob Schlyter
Author-email: jakob@kirei.se
Requires-Python: >=3.12,<4.0
Classifier: License :: OSI Approved :: BSD License
Classifier: Programming Language :: Python :: 3
Classifier: Programming Language :: Python :: 3.12
Classifier: Programming Language :: Python :: 3 :: Only
Classifier: Programming Language :: Python :: 3.10
Classifier: Programming Language :: Python :: 3.11
Classifier: Programming Language :: Python :: 3.9
Requires-Dist: PyJWT (>=2.9.0,<3.0.0)
Requires-Dist: aiohttp (>=3.10.5,<4.0.0)
Requires-Dist: ciso8601 (>=2.3.1,<3.0.0)
Requires-Dist: isoduration (>=20.11.0,<21.0.0)
Requires-Dist: pydantic (>=2.9.2,<3.0.0)
Project-URL: Repository, https://github.com/kirei/python-chargeamps
